environ/__init__.py
environ/__init__.pyi
environ-import/__main__.py
environ_import/__init__.py
environ_import/__main__.py
environ_import/internal.py
environ_import/templates/nullable.txt
environ_import/templates/required.txt
environ_import/util.py
environ_import/watchdog.py
envnull/__init__.py
envnull/__init__.pyi
environ_import-0.1.0.dist-info/METADATA
environ_import-0.1.0.dist-info/WHEEL
environ_import-0.1.0.dist-info/RECORD
