Metadata-Version: 2.1
Name: environ-import
Version: 0.1.0
Summary: A package that allows you to import environment variables like any other module.
Home-page: https://github.com/NimajnebEC/environ-import
License: MIT
Author: NimajnebEC
Author-email: nimajnebec@users.noreply.github.com
Requires-Python: >=3.8.1,<4.0.0
Classifier: License :: OSI Approved :: MIT License
Classifier: Programming Language :: Python :: 3
Classifier: Programming Language :: Python :: 3.9
Classifier: Programming Language :: Python :: 3.10
Classifier: Programming Language :: Python :: 3.11
Requires-Dist: python-dotenv (>=1.0.0,<2.0.0)
Project-URL: Repository, https://github.com/NimajnebEC/environ-import
